umsg/__about__.py
umsg/__init__.py
umsg/core.py
umsg/mixins.py
umsg/util.py
umsg-1.0.4.dist-info/LICENSE
umsg-1.0.4.dist-info/METADATA
umsg-1.0.4.dist-info/WHEEL
umsg-1.0.4.dist-info/top_level.txt
umsg-1.0.4.dist-info/RECORD
